lailib/__init__.py
lailib/image/__init__.py
lailib/image/augment.py
lailib/image/binarize.py
lailib/image/check.py
lailib/image/convert.py
lailib/image/crop.py
lailib/image/resize.py
lailib/image/visualize.py
lailib/torch/__init__.py
lailib/torch/parameter_store.py
lailib-0.1.3.dist-info/LICENSE
lailib-0.1.3.dist-info/METADATA
lailib-0.1.3.dist-info/WHEEL
lailib-0.1.3.dist-info/top_level.txt
lailib-0.1.3.dist-info/RECORD
