Metadata-Version: 2.1
Name: lailib
Version: 0.1.3
Summary: A bag of helper functions
Home-page: https://github.com/learnable-ai/lailib
Author: learnable.ai
Author-email: contact@learnable.ai
License: UNKNOWN
Platform: UNKNOWN
Classifier: Programming Language :: Python :: 3
Classifier: License :: OSI Approved :: MIT License
Classifier: Operating System :: OS Independent
Requires-Python: >=3.6
